cmdcache.py
cmdcache-0.2.1.dist-info/METADATA
cmdcache-0.2.1.dist-info/WHEEL
cmdcache-0.2.1.dist-info/entry_points.txt
cmdcache-0.2.1.dist-info/top_level.txt
cmdcache-0.2.1.dist-info/RECORD
